aerialflightgen/__init__.py
aerialflightgen/cli.py
aerialflightgen/planner.py
aerialflightgen/utils.py
aerialflightgen-0.1.2.dist-info/LICENSE
aerialflightgen-0.1.2.dist-info/METADATA
aerialflightgen-0.1.2.dist-info/WHEEL
aerialflightgen-0.1.2.dist-info/entry_points.txt
aerialflightgen-0.1.2.dist-info/top_level.txt
aerialflightgen-0.1.2.dist-info/RECORD
