Metadata-Version: 2.1
Name: aerialflightgen
Version: 0.1.2
Summary: Custom drone flight plan generator from geojson
Home-page: UNKNOWN
Author: Thirumurugan
License: MIT
Platform: UNKNOWN
Classifier: Programming Language :: Python :: 3
Classifier: License :: OSI Approved :: MIT License
Classifier: Operating System :: OS Independent
Requires-Python: >=3.7
License-File: LICENSE
